{
    "ffvr08m": [
        [
            {
                "Parent ID": "t3_evd39l",
                "Comment ID": "ffvr08m",
                "Author": "Spectrachic311311",
                "Date Created": "01-28-2020 22:07:09",
                "Upvotes": 94,
                "Text": "My doctor took a look at me and said \u201cIt\u2019s terrifying that you have to be skeletal to get good treatment. You are underweight for sure but in LA, you would be normal\u201d. She\u2019s not wrong.",
                "Edited?": false,
                "Is Submitter?": false,
                "Stickied?": false
            }
        ],
        {
            "ffvug54": [
                {
                    "Parent ID": "t1_ffvr08m",
                    "Comment ID": "ffvug54",
                    "Author": "HappierHungry",
                    "Date Created": "01-28-2020 22:53:05",
                    "Upvotes": 59,
                    "Text": "yup, I maintained a BMI of 15-17 when I was modelling (while that wasn't the trigger/sole factor, it certainly didn't help matters) and even my mum would coo at how lucky I was to be *naturally slim*.\n\nit's like an echo chamber of insecurity and shifting goalposts.",
                    "Edited?": false,
                    "Is Submitter?": false,
                    "Stickied?": false
                }
            ],
            "ffvwm5y": [
                [
                    {
                        "Parent ID": "t1_ffvvali",
                        "Comment ID": "ffvwm5y",
                        "Author": "fishonthesun",
                        "Date Created": "01-28-2020 23:24:56",
                        "Upvotes": 28,
                        "Text": "I believe children can be very very low bmi wise compared to adults and be healthy. Like if I had my child BMI now I'd be passing out all the time (I'm like 20 lbs heavier bmi wise right now and still occasionally passing out), but as a child I was perfectly healthy and actually less sick than most children who were at \"healthier\" weights than me\n\nAlthough that's very anecdotal, I dont know for sure!!",
                        "Edited?": false,
                        "Is Submitter?": false,
                        "Stickied?": false
                    }
                ]
            ],
            "ffwz3lh": [
                [
                    {
                        "Parent ID": "t1_ffvvali",
                        "Comment ID": "ffwz3lh",
                        "Author": "froz3nw4ffl3s",
                        "Date Created": "01-29-2020 10:10:43",
                        "Upvotes": 3,
                        "Text": "no, haha, kids can be really small",
                        "Edited?": false,
                        "Is Submitter?": false,
                        "Stickied?": false
                    }
                ]
            ],
            "ffw4gm8": [
                [
                    {
                        "Parent ID": "t1_ffv6wxs",
                        "Comment ID": "ffw4gm8",
                        "Author": "JamesTheKid",
                        "Date Created": "01-29-2020 01:45:16",
                        "Upvotes": 19,
                        "Text": "I lost 10lbs and saw a big difference, but 20? You might be on to something ;)",
                        "Edited?": false,
                        "Is Submitter?": false,
                        "Stickied?": false
                    }
                ],
                {
                    "ffw8bak": [
                        {
                            "Parent ID": "t1_ffw4gm8",
                            "Comment ID": "ffw8bak",
                            "Author": "EnochianMercy",
                            "Date Created": "01-29-2020 03:13:15",
                            "Upvotes": 22,
                            "Text": "You guys are seeing differences? To me my body looks the same, even though i supposedly lost 30lbs (span of half a year).",
                            "Edited?": false,
                            "Is Submitter?": false,
                            "Stickied?": false
                        }
                    ]
                }
            ],
            "ffwj0vv": [
                [
                    {
                        "Parent ID": "t1_ffw8bak",
                        "Comment ID": "ffwj0vv",
                        "Author": "BBspoonie",
                        "Date Created": "01-29-2020 06:56:55",
                        "Upvotes": 5,
                        "Text": "Literally the exact same situation for me, pounds and timeframe lol, and of course still thinking I look the exact same size as before??!?",
                        "Edited?": false,
                        "Is Submitter?": false,
                        "Stickied?": false
                    }
                ]
            ]
        }
    ],
    "ffv83sv": [
        [
            {
                "Parent ID": "t3_evd39l",
                "Comment ID": "ffv83sv",
                "Author": "froz3nw4ffl3s",
                "Date Created": "01-28-2020 18:32:17",
                "Upvotes": 70,
                "Text": "yeah my mom is peak \"american 'healthy' weight is actually overweight\" and i feel like if i told her about my eating habits she'd be like \"but no you're not skinny!!1!!!1 you just eat less compared to americans who eat four burgers a day xoxo\" \n\nlike i remember going to the doctor when i was 10 for my yearly checkup and i was slightly below average bmi but still healthy (like 15.8) and my mom was like \"no that doesn't mean anything americans don't know what beauty really is\"",
                "Edited?": false,
                "Is Submitter?": false,
                "Stickied?": false
            }
        ],
        {
            "ffvcacj": [
                {
                    "Parent ID": "t1_ffv83sv",
                    "Comment ID": "ffvcacj",
                    "Author": "incompetentbeing",
                    "Date Created": "01-28-2020 19:19:02",
                    "Upvotes": 75,
                    "Text": "My mom is the exact same! Just last week I opened up to her about how dark my life was at my lowest weight, and she said, \"well you were never *that* skinny. Like not skinnier than the women in movies.\" My BMI was 16, I had no period, hair was falling out, fainting spells, all that. She didn't even mean it maliciously. She's just oblivious. People think you have to be at-death's-door-most-people-don't-survive skinny to have a serious problem.",
                    "Edited?": false,
                    "Is Submitter?": false,
                    "Stickied?": false
                }
            ],
            "ffvwm5y": [
                [
                    {
                        "Parent ID": "t1_ffvvali",
                        "Comment ID": "ffvwm5y",
                        "Author": "fishonthesun",
                        "Date Created": "01-28-2020 23:24:56",
                        "Upvotes": 28,
                        "Text": "I believe children can be very very low bmi wise compared to adults and be healthy. Like if I had my child BMI now I'd be passing out all the time (I'm like 20 lbs heavier bmi wise right now and still occasionally passing out), but as a child I was perfectly healthy and actually less sick than most children who were at \"healthier\" weights than me\n\nAlthough that's very anecdotal, I dont know for sure!!",
                        "Edited?": false,
                        "Is Submitter?": false,
                        "Stickied?": false
                    }
                ]
            ],
            "ffwz3lh": [
                [
                    {
                        "Parent ID": "t1_ffvvali",
                        "Comment ID": "ffwz3lh",
                        "Author": "froz3nw4ffl3s",
                        "Date Created": "01-29-2020 10:10:43",
                        "Upvotes": 3,
                        "Text": "no, haha, kids can be really small",
                        "Edited?": false,
                        "Is Submitter?": false,
                        "Stickied?": false
                    }
                ]
            ],
            "ffw4gm8": [
                [
                    {
                        "Parent ID": "t1_ffv6wxs",
                        "Comment ID": "ffw4gm8",
                        "Author": "JamesTheKid",
                        "Date Created": "01-29-2020 01:45:16",
                        "Upvotes": 19,
                        "Text": "I lost 10lbs and saw a big difference, but 20? You might be on to something ;)",
                        "Edited?": false,
                        "Is Submitter?": false,
                        "Stickied?": false
                    }
                ],
                {
                    "ffw8bak": [
                        {
                            "Parent ID": "t1_ffw4gm8",
                            "Comment ID": "ffw8bak",
                            "Author": "EnochianMercy",
                            "Date Created": "01-29-2020 03:13:15",
                            "Upvotes": 22,
                            "Text": "You guys are seeing differences? To me my body looks the same, even though i supposedly lost 30lbs (span of half a year).",
                            "Edited?": false,
                            "Is Submitter?": false,
                            "Stickied?": false
                        }
                    ]
                }
            ],
            "ffwj0vv": [
                [
                    {
                        "Parent ID": "t1_ffw8bak",
                        "Comment ID": "ffwj0vv",
                        "Author": "BBspoonie",
                        "Date Created": "01-29-2020 06:56:55",
                        "Upvotes": 5,
                        "Text": "Literally the exact same situation for me, pounds and timeframe lol, and of course still thinking I look the exact same size as before??!?",
                        "Edited?": false,
                        "Is Submitter?": false,
                        "Stickied?": false
                    }
                ]
            ]
        },
        {
            "ffvvali": [
                {
                    "Parent ID": "t1_ffv83sv",
                    "Comment ID": "ffvvali",
                    "Author": "chubster157",
                    "Date Created": "01-28-2020 23:05:11",
                    "Upvotes": 12,
                    "Text": "Do you mean 18.5?",
                    "Edited?": false,
                    "Is Submitter?": false,
                    "Stickied?": false
                },
                {
                    "ffvwm5y": [
                        {
                            "Parent ID": "t1_ffvvali",
                            "Comment ID": "ffvwm5y",
                            "Author": "fishonthesun",
                            "Date Created": "01-28-2020 23:24:56",
                            "Upvotes": 28,
                            "Text": "I believe children can be very very low bmi wise compared to adults and be healthy. Like if I had my child BMI now I'd be passing out all the time (I'm like 20 lbs heavier bmi wise right now and still occasionally passing out), but as a child I was perfectly healthy and actually less sick than most children who were at \"healthier\" weights than me\n\nAlthough that's very anecdotal, I dont know for sure!!",
                            "Edited?": false,
                            "Is Submitter?": false,
                            "Stickied?": false
                        }
                    ]
                },
                {
                    "ffwz3lh": [
                        {
                            "Parent ID": "t1_ffvvali",
                            "Comment ID": "ffwz3lh",
                            "Author": "froz3nw4ffl3s",
                            "Date Created": "01-29-2020 10:10:43",
                            "Upvotes": 3,
                            "Text": "no, haha, kids can be really small",
                            "Edited?": false,
                            "Is Submitter?": false,
                            "Stickied?": false
                        }
                    ]
                }
            ],
            "ffw4gm8": [
                [
                    {
                        "Parent ID": "t1_ffv6wxs",
                        "Comment ID": "ffw4gm8",
                        "Author": "JamesTheKid",
                        "Date Created": "01-29-2020 01:45:16",
                        "Upvotes": 19,
                        "Text": "I lost 10lbs and saw a big difference, but 20? You might be on to something ;)",
                        "Edited?": false,
                        "Is Submitter?": false,
                        "Stickied?": false
                    }
                ],
                {
                    "ffw8bak": [
                        {
                            "Parent ID": "t1_ffw4gm8",
                            "Comment ID": "ffw8bak",
                            "Author": "EnochianMercy",
                            "Date Created": "01-29-2020 03:13:15",
                            "Upvotes": 22,
                            "Text": "You guys are seeing differences? To me my body looks the same, even though i supposedly lost 30lbs (span of half a year).",
                            "Edited?": false,
                            "Is Submitter?": false,
                            "Stickied?": false
                        }
                    ]
                }
            ],
            "ffwj0vv": [
                [
                    {
                        "Parent ID": "t1_ffw8bak",
                        "Comment ID": "ffwj0vv",
                        "Author": "BBspoonie",
                        "Date Created": "01-29-2020 06:56:55",
                        "Upvotes": 5,
                        "Text": "Literally the exact same situation for me, pounds and timeframe lol, and of course still thinking I look the exact same size as before??!?",
                        "Edited?": false,
                        "Is Submitter?": false,
                        "Stickied?": false
                    }
                ]
            ]
        }
    ],
    "ffvqk03": [
        [
            {
                "Parent ID": "t3_evd39l",
                "Comment ID": "ffvqk03",
                "Author": "throneofweigh",
                "Date Created": "01-28-2020 22:01:24",
                "Upvotes": 58,
                "Text": "guys some people are just naturally skinny !!! *picture of a girl with a bmi of 16*",
                "Edited?": false,
                "Is Submitter?": false,
                "Stickied?": false
            }
        ]
    ],
    "ffv2i1u": [
        [
            {
                "Parent ID": "t3_evd39l",
                "Comment ID": "ffv2i1u",
                "Author": "meowmehungry",
                "Date Created": "01-28-2020 17:29:30",
                "Upvotes": 125,
                "Text": "Yeah it\u2019s normal and attractive to be a BMI of 17-18 \ud83e\udd26\ud83c\udffb\u200d\u2640\ufe0f",
                "Edited?": false,
                "Is Submitter?": false,
                "Stickied?": false
            }
        ],
        {
            "ffv6wxs": [
                {
                    "Parent ID": "t1_ffv2i1u",
                    "Comment ID": "ffv6wxs",
                    "Author": "20lbsfast",
                    "Date Created": "01-28-2020 18:18:43",
                    "Upvotes": 100,
                    "Text": "Its true. My BMI hits 20 no comments about my body at all.  As soon as I hit 18 my body is praised to the heavens. Its actually insane how much of a difference 20 lbs can make (thus the user name).",
                    "Edited?": false,
                    "Is Submitter?": false,
                    "Stickied?": false
                },
                {
                    "ffw4gm8": [
                        {
                            "Parent ID": "t1_ffv6wxs",
                            "Comment ID": "ffw4gm8",
                            "Author": "JamesTheKid",
                            "Date Created": "01-29-2020 01:45:16",
                            "Upvotes": 19,
                            "Text": "I lost 10lbs and saw a big difference, but 20? You might be on to something ;)",
                            "Edited?": false,
                            "Is Submitter?": false,
                            "Stickied?": false
                        }
                    ]
                }
            ],
            "ffvwm5y": [
                [
                    {
                        "Parent ID": "t1_ffvvali",
                        "Comment ID": "ffvwm5y",
                        "Author": "fishonthesun",
                        "Date Created": "01-28-2020 23:24:56",
                        "Upvotes": 28,
                        "Text": "I believe children can be very very low bmi wise compared to adults and be healthy. Like if I had my child BMI now I'd be passing out all the time (I'm like 20 lbs heavier bmi wise right now and still occasionally passing out), but as a child I was perfectly healthy and actually less sick than most children who were at \"healthier\" weights than me\n\nAlthough that's very anecdotal, I dont know for sure!!",
                        "Edited?": false,
                        "Is Submitter?": false,
                        "Stickied?": false
                    }
                ]
            ],
            "ffwz3lh": [
                [
                    {
                        "Parent ID": "t1_ffvvali",
                        "Comment ID": "ffwz3lh",
                        "Author": "froz3nw4ffl3s",
                        "Date Created": "01-29-2020 10:10:43",
                        "Upvotes": 3,
                        "Text": "no, haha, kids can be really small",
                        "Edited?": false,
                        "Is Submitter?": false,
                        "Stickied?": false
                    }
                ]
            ],
            "ffw8bak": [
                [
                    {
                        "Parent ID": "t1_ffw4gm8",
                        "Comment ID": "ffw8bak",
                        "Author": "EnochianMercy",
                        "Date Created": "01-29-2020 03:13:15",
                        "Upvotes": 22,
                        "Text": "You guys are seeing differences? To me my body looks the same, even though i supposedly lost 30lbs (span of half a year).",
                        "Edited?": false,
                        "Is Submitter?": false,
                        "Stickied?": false
                    }
                ],
                {
                    "ffwj0vv": [
                        {
                            "Parent ID": "t1_ffw8bak",
                            "Comment ID": "ffwj0vv",
                            "Author": "BBspoonie",
                            "Date Created": "01-29-2020 06:56:55",
                            "Upvotes": 5,
                            "Text": "Literally the exact same situation for me, pounds and timeframe lol, and of course still thinking I look the exact same size as before??!?",
                            "Edited?": false,
                            "Is Submitter?": false,
                            "Stickied?": false
                        }
                    ]
                }
            ]
        }
    ],
    "ffwcklm": [
        [
            {
                "Parent ID": "t3_evd39l",
                "Comment ID": "ffwcklm",
                "Author": "lezuza",
                "Date Created": "01-29-2020 04:56:51",
                "Upvotes": 23,
                "Text": "Kpop stans are shaking",
                "Edited?": false,
                "Is Submitter?": false,
                "Stickied?": false
            }
        ]
    ],
    "ffw7wye": [
        [
            {
                "Parent ID": "t3_evd39l",
                "Comment ID": "ffw7wye",
                "Author": "sciencevigilante",
                "Date Created": "01-29-2020 03:03:16",
                "Upvotes": 21,
                "Text": "BMI hits underweight and I get compliments on my calves from strangers. Thanks, it\u2019s my organic proprietary blend of compulsive exercise, malnutrition, and self hatred.",
                "Edited?": false,
                "Is Submitter?": false,
                "Stickied?": false
            }
        ]
    ],
    "ffwcmwh": [
        [
            {
                "Parent ID": "t3_evd39l",
                "Comment ID": "ffwcmwh",
                "Author": "b-ees",
                "Date Created": "01-29-2020 04:58:17",
                "Upvotes": 6,
                "Text": "facts!! but also underweight people could very well not have an ED but just don't eat enough, like the \"she posted a pic of a burger once\"! bro my sis is underweight but bc she's really picky and only eats food she likes therefore she doesn't eat that much but she still eats!! saying someone is underweight doesn't have to mean they have eating issues but they are more than likely at least a little physically unhealthy.",
                "Edited?": false,
                "Is Submitter?": false,
                "Stickied?": false
            }
        ]
    ],
    "ffv8gro": [
        [
            {
                "Parent ID": "t3_evd39l",
                "Comment ID": "ffv8gro",
                "Author": "[deleted]",
                "Date Created": "01-28-2020 18:36:17",
                "Upvotes": 22,
                "Text": "[removed]",
                "Edited?": false,
                "Is Submitter?": false,
                "Stickied?": false
            }
        ],
        {
            "ffvep4x": [
                {
                    "Parent ID": "t1_ffv8gro",
                    "Comment ID": "ffvep4x",
                    "Author": "KrypticKricket",
                    "Date Created": "01-28-2020 19:46:07",
                    "Upvotes": 21,
                    "Text": "15 or 16 ??",
                    "Edited?": false,
                    "Is Submitter?": false,
                    "Stickied?": false
                }
            ],
            "ffvwm5y": [
                [
                    {
                        "Parent ID": "t1_ffvvali",
                        "Comment ID": "ffvwm5y",
                        "Author": "fishonthesun",
                        "Date Created": "01-28-2020 23:24:56",
                        "Upvotes": 28,
                        "Text": "I believe children can be very very low bmi wise compared to adults and be healthy. Like if I had my child BMI now I'd be passing out all the time (I'm like 20 lbs heavier bmi wise right now and still occasionally passing out), but as a child I was perfectly healthy and actually less sick than most children who were at \"healthier\" weights than me\n\nAlthough that's very anecdotal, I dont know for sure!!",
                        "Edited?": false,
                        "Is Submitter?": false,
                        "Stickied?": false
                    }
                ]
            ],
            "ffwz3lh": [
                [
                    {
                        "Parent ID": "t1_ffvvali",
                        "Comment ID": "ffwz3lh",
                        "Author": "froz3nw4ffl3s",
                        "Date Created": "01-29-2020 10:10:43",
                        "Upvotes": 3,
                        "Text": "no, haha, kids can be really small",
                        "Edited?": false,
                        "Is Submitter?": false,
                        "Stickied?": false
                    }
                ]
            ],
            "ffw4gm8": [
                [
                    {
                        "Parent ID": "t1_ffv6wxs",
                        "Comment ID": "ffw4gm8",
                        "Author": "JamesTheKid",
                        "Date Created": "01-29-2020 01:45:16",
                        "Upvotes": 19,
                        "Text": "I lost 10lbs and saw a big difference, but 20? You might be on to something ;)",
                        "Edited?": false,
                        "Is Submitter?": false,
                        "Stickied?": false
                    }
                ],
                {
                    "ffw8bak": [
                        {
                            "Parent ID": "t1_ffw4gm8",
                            "Comment ID": "ffw8bak",
                            "Author": "EnochianMercy",
                            "Date Created": "01-29-2020 03:13:15",
                            "Upvotes": 22,
                            "Text": "You guys are seeing differences? To me my body looks the same, even though i supposedly lost 30lbs (span of half a year).",
                            "Edited?": false,
                            "Is Submitter?": false,
                            "Stickied?": false
                        }
                    ]
                }
            ],
            "ffwj0vv": [
                [
                    {
                        "Parent ID": "t1_ffw8bak",
                        "Comment ID": "ffwj0vv",
                        "Author": "BBspoonie",
                        "Date Created": "01-29-2020 06:56:55",
                        "Upvotes": 5,
                        "Text": "Literally the exact same situation for me, pounds and timeframe lol, and of course still thinking I look the exact same size as before??!?",
                        "Edited?": false,
                        "Is Submitter?": false,
                        "Stickied?": false
                    }
                ]
            ]
        }
    ]
}